py_tgi/__init__.py
py_tgi/inference_server.py
py_tgi/text_embedding_inference.py
py_tgi/text_generation_inference.py
py_tgi/utils.py
py_tgi-0.2.0.dist-info/METADATA
py_tgi-0.2.0.dist-info/WHEEL
py_tgi-0.2.0.dist-info/top_level.txt
py_tgi-0.2.0.dist-info/RECORD
