Metadata-Version: 2.1
Name: py-tgi
Version: 0.2.0
Summary: A Python wrapper around TGI and TEI servers
Home-page: https://github.com/IlyasMoutawwakil/py-tgi
Author: Ilyas Moutawwakil
Author-email: ilyas.moutawwakil@gmail.com
Keywords: tgi,llm,tei,embedding,huggingface,docker,python
Platform: linux
Platform: windows
Platform: macos
Classifier: Programming Language :: Python :: 3
Classifier: Natural Language :: English
Requires-Dist: docker
Requires-Dist: huggingface-hub
Requires-Dist: numpy
Provides-Extra: quality
Requires-Dist: ruff ; extra == 'quality'
